dkrlog/__init__.py
dkrlog-2.3.dist-info/LICENSE
dkrlog-2.3.dist-info/METADATA
dkrlog-2.3.dist-info/WHEEL
dkrlog-2.3.dist-info/top_level.txt
dkrlog-2.3.dist-info/RECORD
