Metadata-Version: 2.2
Name: dkrlog
Version: 2.3
Summary: This library standardizes logs and exceptions, ensuring consistent error handling and tracking.
Author: Leticia Figueiredo
Author-email: Leticia Figueiredo <leticia.figueiredo@dkr.tec.br>
Classifier: Programming Language :: Python :: 3
Classifier: License :: OSI Approved :: MIT License
Classifier: Operating System :: OS Independent
Requires-Python: >=3.7
License-File: LICENSE
Requires-Dist: requests
Requires-Dist: pytz
Requires-Dist: logzero
Requires-Dist: sqlalchemy
Requires-Dist: psycopg2-binary
Dynamic: author
Dynamic: requires-python
